{
  "producer_account_name": "chainriftxxx",
  "producer_public_key": "EOS7RQ6fJTDzZTSoL6tmzXwfs9FLZTUPWDe6pNAhqqWHvcAxG7qdN",
  "org": {
    "candidate_name": "Chainrift",
    "website": "https://eos.chainrift.com",
    "code_of_conduct": "https://en.wikipedia.org/wiki/Golden_Rule",
    "email": "mourad@21mil.com",
    "branding": {
      "logo_256": "https://www.chainrift.com/images/logo.png",
      "logo_1024": "https://www.chainrift.com/images/fbimage.png",
      "logo_svg": ""
    },
    "location": {
      "name": "Ljubljana",
      "country": "SI",
      "latitude": 46.056946,
      "longitude": 14.505751
    },
    "social": {
      "steemit": "chainrift",
      "twitter": "chainrift",
      "youtube": "",
      "facebook": "ChainRift-478946299144430",
      "github": "ChainRift",
      "reddit": "ChainRift",
      "keybase": "ChainRift",
      "telegram": "ChainRift Community",
      "wechat": ""
    }
  },
  "nodes": [
    {
      "location": {
        "name": "Ljubljana",
        "country": "SI",
        "latitude": 46.056946,
        "longitude": 14.505751
      },
      "is_producer": false,
      "p2p_endpoint": "eosboot.chainrift.com:9876",
      "api_endpoint": "",
      "ssl_endpoint": "https://eospublic.chainrift.com"
    },
    {
      "location": {
        "name": "Frankfurt",
        "country": "DEU",
        "latitude": 50.110924,
        "longitude": 8.682127
      },
      "is_producer": true,
      "p2p_endpoint": "",
      "api_endpoint": "",
      "ssl_endpoint": ""
    }
  ]
}