{
  "producer_account_name": "eosiosg11111",
  "org": {
    "candidate_name": "EOSIO.SG",
    "website": "https://eosio.sg",
    "email": "deadlock@eosio.sg",
    "branding": {
      "logo_256": "https://image.eosio.sg/EOSIOSG_256.png",
      "logo_1024": "https://image.eosio.sg/EOSIOSG_1024.png",
      "logo_svg": "https://image.eosio.sg/EOSIOSG.svg"
    },
    "location": {
      "name": "Singapore",
      "country": "SG",
      "latitude": 1.29027,
      "longitude": 103.851959
    },
    "social": {
      "steemit": "eosiosg",
      "twitter": "eosiosg",
      "facebook": "eosiosg-168790343770758",
      "github": "eosiosg",
      "telegram": "eosiosg"
    }
  },
  "nodes": [
    {
      "location": {
        "name": "Taiwan",
        "country": "TW",
        "latitude": 25.105497,
        "longitude": 121.597366
      },
      "node_type": "full",
      "api_endpoint": "http://mainnet.eosio.sg",
      "ssl_endpoint": "https://mainnet.eosio.sg"
    },
    {
      "location": {
        "name": "Taiwan",
        "country": "TW",
        "latitude": 25.105497,
        "longitude": 121.597366
      },
      "node_type": "seed",
      "p2p_endpoint": "peer.eosio.sg:80"
    },
    {
      "location": {
        "name": "Singapore",
        "country": "SG",
        "latitude": 1.29027,
        "longitude": 103.851959
      },
      "node_type": "producer"
    }
  ]
}